yundownload/__init__.py
yundownload/core/__init__.py
yundownload/core/downloader.py
yundownload/core/resources.py
yundownload/network/__init__.py
yundownload/network/base.py
yundownload/network/ftp.py
yundownload/network/http.py
yundownload/network/m3u.py
yundownload/network/sftp.py
yundownload/utils/__init__.py
yundownload/utils/cli.py
yundownload/utils/config.py
yundownload/utils/core.py
yundownload/utils/equilibrium.py
yundownload/utils/exceptions.py
yundownload/utils/logger.py
yundownload/utils/tools.py
yundownload/utils/work.py
yundownload/version.py
yundownload-0.6.21.dist-info/METADATA
yundownload-0.6.21.dist-info/WHEEL
yundownload-0.6.21.dist-info/entry_points.txt
yundownload-0.6.21.dist-info/licenses/LICENSE
yundownload-0.6.21.dist-info/RECORD
