Metadata-Version: 2.4
Name: yundownload
Version: 0.6.21
Summary: file downloader
License: MIT
License-File: LICENSE
Author: yunhai
Author-email: bybxbwg@foxmail.com
Requires-Python: >=3.10,<4.0
Classifier: License :: OSI Approved :: MIT License
Classifier: Programming Language :: Python :: 3
Classifier: Programming Language :: Python :: 3.10
Classifier: Programming Language :: Python :: 3.11
Classifier: Programming Language :: Python :: 3.12
Classifier: Programming Language :: Python :: 3.13
Classifier: Programming Language :: Python :: 3.14
Requires-Dist: aiofiles (>=24.1.0,<25.0.0)
Requires-Dist: colorlog (>=6.9.0,<7.0.0)
Requires-Dist: httpx (>=0.28.1,<0.29.0)
Requires-Dist: m3u8 (>=6.0.0,<7.0.0)
Requires-Dist: paramiko (>=3.5.1,<4.0.0)
Requires-Dist: pycryptodome (>=3.23.0,<4.0.0)
